UzMorphAnalyser/UzMorphAnalyser.py
UzMorphAnalyser/__init__.py
UzMorphAnalyser/affixes.csv
UzMorphAnalyser/exception_stems.csv
UzMorphAnalyser/lemma_map.csv
UzMorphAnalyser/non_affixed_stems.csv
UzMorphAnalyser/number_stems.csv
UzMorphAnalyser/small_stems.csv
UzMorphAnalyser-0.0.19.dist-info/LICENSE
UzMorphAnalyser-0.0.19.dist-info/METADATA
UzMorphAnalyser-0.0.19.dist-info/WHEEL
UzMorphAnalyser-0.0.19.dist-info/top_level.txt
UzMorphAnalyser-0.0.19.dist-info/RECORD
