Metadata-Version: 2.1
Name: UzMorphAnalyser
Version: 0.0.19
Summary: UzMorphAnalyser | Uzbek Morphological Analyser on Python
Home-page: https://github.com/UlugbekSalaev/UzMorphAnalyser
Author: Ulugbek Salaev
Author-email: ulugbek0302@gmail.com
Project-URL: Bug Tracker, https://github.com/UlugbekSalaev/UzMorphAnalyser/issues
Keywords: mophology,uzbek-language,stemmer,lemmatize,morphological analysis
Classifier: Programming Language :: Python :: 3
Classifier: License :: OSI Approved :: MIT License
Classifier: Operating System :: OS Independent
Requires-Python: >=3.6
License-File: LICENSE
